benchtemp/__init__.py
benchtemp/core/__init__.py
benchtemp/core/api.py
benchtemp/lp/__init__.py
benchtemp/lp/dataloader.py
benchtemp/lp/edgesampler.py
benchtemp/nc/__init__.py
benchtemp/nc/dataloader.py
benchtemp/optimization/__init__.py
benchtemp/optimization/loss.py
benchtemp/optimization/optimizer.py
benchtemp/preprocess/__init__.py
benchtemp/preprocess/preprocessing.py
benchtemp/utils/__init__.py
benchtemp/utils/earlystop_monitor.py
benchtemp/utils/evaluator.py
benchtemp/utils/temporal_data.py
benchtemp-1.1.1.dist-info/METADATA
benchtemp-1.1.1.dist-info/WHEEL
benchtemp-1.1.1.dist-info/entry_points.txt
benchtemp-1.1.1.dist-info/license_files/LICENSE
benchtemp-1.1.1.dist-info/RECORD
