Metadata-Version: 2.1
Name: benchtemp
Version: 1.1.1
Summary: BenchTemp: A General Benchmark for Evaluating Temporal Graph Neural Networks
Project-URL: Bug Tracker, https://github.com/qianghuangwhu/benchtemp/issues
Project-URL: Homepage, https://github.com/qianghuangwhu/benchtemp
Author-email: Qiang Huang <jonnyhuanghnu@gmail.com>
Classifier: License :: OSI Approved :: MIT License
Classifier: Operating System :: OS Independent
Classifier: Programming Language :: Python :: 3
Requires-Python: >=3.6
